{
  "forge:registry_name": "afraidofthedark:apprentice_ascended",
  "recipes": [],
  "pre_recipes": [],
  "icon": "afraidofthedark:textures/gui/research_icons/apprentice_ascended.png",
  "prerequisite": "afraidofthedark:arch_sorceress",
  "triggers": [
    {
      "type": "afraidofthedark:use_block",
      "config": {
        "block_or_state": "afraidofthedark:enarias_altar"
      }
    }
  ],
  "spell_components": {
    "delivery_methods": [
      "afraidofthedark:laser",
      "afraidofthedark:delay",
      "afraidofthedark:chain",
      "afraidofthedark:wall"
    ],
    "effects": [
      "afraidofthedark:feed",
      "afraidofthedark:grow",
      "afraidofthedark:heal",
      "afraidofthedark:dig",
      "afraidofthedark:ward"
    ]
  }
}