{
  "forge:registry_name": "afraidofthedark:wisdom",
  "recipes": [],
  "pre_recipes": [],
  "icon": "afraidofthedark:textures/gui/research_icons/wisdom.png",
  "prerequisite": "afraidofthedark:reanimation",
  "triggers": [
    {
      "type": "afraidofthedark:multiplicity",
      "config": {
        "base_trigger": {
          "type": "afraidofthedark:kill_entity",
          "config": {
            "entity_type": "afraidofthedark:enchanted_skeleton"
          }
        },
        "times": 15,
        "key": "afraidofthedark:enchanted_skeleton_kills"
      }
    }
  ]
}